AUTHORS.rst
LICENSE.txt
MANIFEST.in
README.rst
setup.py
django_profiling_dashboard_fc.egg-info/PKG-INFO
django_profiling_dashboard_fc.egg-info/SOURCES.txt
django_profiling_dashboard_fc.egg-info/dependency_links.txt
django_profiling_dashboard_fc.egg-info/requires.txt
django_profiling_dashboard_fc.egg-info/top_level.txt
profiling_dashboard/__init__.py
profiling_dashboard/forms.py
profiling_dashboard/stats.py
profiling_dashboard/urls.py
profiling_dashboard/views.py
profiling_dashboard/templates/profiling_dashboard/base.html
profiling_dashboard/templates/profiling_dashboard/cpu.html
profiling_dashboard/templates/profiling_dashboard/memory.html
profiling_dashboard/templates/profiling_dashboard/process_info.html
profiling_dashboard/templates/profiling_dashboard/web_top.html