Metadata-Version: 1.0
Name: django-profiling-dashboard-fc
Version: 1.0
Summary:  Django profiling dashboard for debugging CPU, memory and other resources usage in live servers 
Home-page: https://github.com/kmike/django-profiling-dashboard
Author: Mikhail Korobov
Author-email: kmike84@gmail.com
License: MIT license
Download-URL: https://github.com/kmike/django-profiling-dashboard/zipball/master
Platform: UNKNOWN
Classifier: Development Status :: 3 - Alpha
Classifier: Environment :: Web Environment
Classifier: Framework :: Django
Classifier: Intended Audience :: Developers
Classifier: Intended Audience :: System Administrators
Classifier: License :: OSI Approved :: MIT License
Classifier: Programming Language :: Python
Classifier: Programming Language :: Python :: 2.6
Classifier: Programming Language :: Python :: 2.7
Classifier: Programming Language :: Python :: Implementation :: CPython
Classifier: Topic :: Software Development :: Libraries :: Python Modules
